{
  "defaultcard": "list",
  "displaychecked": false,
  "tableofcontents": false,
  "groups": {
  	"Posts" : {
    		"comment": "The HeritagePIDs blog contains case studies describing use cases for persistent identifiers (PIDs) and requirements different organisations have for them. Content on the blog is updated regularly.",
    		"card": "list"}
  	},
  "list": [{
  "groups": ["Posts"],
  "ptitle": "Linked Conservation Data and PIDs",
	"stitle": "",
	"comment": "",
	"image": "",
	"checked": "",
	"link": "https://tanc-ahrc.github.io/HeritagePIDs/LCD%20Blog.html"
},{
  "groups": ["Posts"],
	"ptitle": "Identifiers at the V&A - A Case Study",
	"stitle": "",
	"comment": "",
	"image": "",
	"checked": "",
	"link": "https://tanc-ahrc.github.io/HeritagePIDs/V&A%20Case%20Study.html"
},{
  "groups": ["Posts"],
	"ptitle": "PIDs for Places",
	"stitle": "",
	"comment": "",
	"image": "",
	"checked": "",
	"link": "https://tanc-ahrc.github.io/HeritagePIDs/PIDs%20for%20Places.html"
},{
  "groups": ["Posts"],
	"ptitle": "Aggregating archive data with and without PIDs",
	"stitle": "",
	"comment": "",
	"image": "",
	"checked": "",
	"link": "https://tanc-ahrc.github.io/HeritagePIDs/Archives%20Hub.html"
},{
  "groups": ["Posts"],
	"ptitle": "Developing \"Developing Identifiers for Heritage Collections\"",
	"stitle": "",
	"comment": "",
	"image": "",
	"checked": "",
	"link": "https://tanc-ahrc.github.io/HeritagePIDs/Developing%20IDs%20Blog.html"
},{
  "groups": ["Posts"],
	"ptitle": "Developing Identifiers for heritage Collections – the new edition",
	"stitle": "",
	"comment": "",
	"image": "",
	"checked": "",
	"link": "https://tanc-ahrc.github.io/HeritagePIDs/Developing%20IDs%20Revisions.html"
	},{
  "groups": ["Posts"],
	"ptitle": "Persistent identifiers in IIIF resources - how should they be used?",
	"stitle": "",
	"comment": "",
	"image": "",
	"checked": "",
	"link": "https://tanc-ahrc.github.io/HeritagePIDs/PIDs%20and%20IIIF.html"
}]
	
}
